beautiful_barcode/__init__.py
beautiful_barcode/__main__.py
beautiful_barcode/barcode.py
beautiful_barcode/ean.py
beautiful_barcode/renderers.py
beautiful_barcode/upc.py
beautiful_barcode/utils.py
beautiful_barcode-1.1.3.dist-info/LICENSE
beautiful_barcode-1.1.3.dist-info/WHEEL
beautiful_barcode-1.1.3.dist-info/METADATA
beautiful_barcode-1.1.3.dist-info/RECORD
