Metadata-Version: 2.1
Name: beautiful-barcode
Version: 1.1.3
Summary: Generate nicely formatted barcodes (UPC-A and EAN)
License: MIT
Keywords: barcode,UPC
Author: Philipp Hagemeister
Author-email: phihag@phihag.de
Requires-Python: >=3.6,<4.0.0
Classifier: Development Status :: 5 - Production/Stable
Classifier: Intended Audience :: Developers
Classifier: License :: OSI Approved :: MIT License
Classifier: Programming Language :: Python :: 3
Classifier: Programming Language :: Python :: 3.10
Classifier: Programming Language :: Python :: 3.6
Classifier: Programming Language :: Python :: 3.7
Classifier: Programming Language :: Python :: 3.8
Classifier: Programming Language :: Python :: 3.9
Classifier: Topic :: Software Development :: Libraries :: Python Modules
